{

  "model_step": "flow",
  "preceding_step": ["climate"],
  "model_description": "this is abcde model developed by austin and scott, flow coefficients regionalized by basin area",

  "userid": {
    "required": 1,
    "description": "Always required, to be included in all config files."
  },
  "runid": {
    "required": 1,
    "description": "Always required, to be included in all config files."
  },
  "basinid": {
    "required": 1,
    "description": "NHDplus featureid or name of preset basin (i.e. west_brook)"
  },
  "rscript": {
    "required": 1,
	 "description": "Name of the script that this config file is for. Always required, to be included in all config files."
  },

  
  "basin_area": {
	"default":51,
	"description":"not used. was temporarily used before area was included in basin param file."
  },
  
  
  
  "preceding": {
	 "description": "json object of step: runid pairs. must include a pair for every step listed in this config file's preceding_step array"
  }

}
